Metadata-Version: 2.1
Name: wrapper-mysql-connector
Version: 0.0.2
Summary: Wrapper não oficial do mysql-connector
Author: Renan de Souza Rodrigues
Author-email: renanrodrigues7110@gmail.com
License: MIT License
Keywords: mysql,mysql-connector,wrapper,wrapper-mysql,wrapper-mysql-connector
License-File: LICENCE
Requires-Dist: mysql-connector-python
